odoo/addons/sale_stock_picking_invoice_link/README.rst
odoo/addons/sale_stock_picking_invoice_link/__init__.py
odoo/addons/sale_stock_picking_invoice_link/__manifest__.py
odoo/addons/sale_stock_picking_invoice_link/i18n/it.po
odoo/addons/sale_stock_picking_invoice_link/i18n/sale_stock_picking_invoice_link.pot
odoo/addons/sale_stock_picking_invoice_link/models/__init__.py
odoo/addons/sale_stock_picking_invoice_link/models/sale_order.py
odoo/addons/sale_stock_picking_invoice_link/models/stock_move.py
odoo/addons/sale_stock_picking_invoice_link/readme/CONTRIBUTORS.md
odoo/addons/sale_stock_picking_invoice_link/readme/DESCRIPTION.md
odoo/addons/sale_stock_picking_invoice_link/readme/USAGE.md
odoo/addons/sale_stock_picking_invoice_link/static/description/icon.png
odoo/addons/sale_stock_picking_invoice_link/static/description/index.html
odoo/addons/sale_stock_picking_invoice_link/tests/__init__.py
odoo/addons/sale_stock_picking_invoice_link/tests/test_stock_picking_invoice_link.py
odoo_addon_sale_stock_picking_invoice_link-18.0.1.0.0.3.dist-info/METADATA
odoo_addon_sale_stock_picking_invoice_link-18.0.1.0.0.3.dist-info/WHEEL
odoo_addon_sale_stock_picking_invoice_link-18.0.1.0.0.3.dist-info/top_level.txt
odoo_addon_sale_stock_picking_invoice_link-18.0.1.0.0.3.dist-info/RECORD
