Metadata-Version: 2.1
Name: odoo-addon-sale_stock_picking_invoice_link
Version: 18.0.1.0.0.3
Requires-Python: >=3.10
Requires-Dist: odoo-addon-stock_picking_invoice_link==18.0.*
Requires-Dist: odoo==18.0.*
Summary: Adds link between pickings and invoices
Home-page: https://github.com/OCA/stock-logistics-workflow
License: AGPL-3
Author: Agile Business Group, Tecnativa, BCIM sprl, Softdil S.L, Akretion, Odoo Community Association (OCA)
Author-email: support@odoo-community.org
Classifier: Programming Language :: Python
Classifier: Framework :: Odoo
Classifier: Framework :: Odoo :: 18.0
Classifier: License :: OSI Approved :: GNU Affero General Public License v3
